cytogis/__init__.py
cytogis/features.py
cytogis/gismanager.py
cytogis-0.1.0.dist-info/LICENSE
cytogis-0.1.0.dist-info/METADATA
cytogis-0.1.0.dist-info/WHEEL
cytogis-0.1.0.dist-info/top_level.txt
cytogis-0.1.0.dist-info/RECORD
