Metadata-Version: 2.1
Name: cytogis
Version: 0.1.0
Summary: cyto to gis is a small package to convert .cyjs files from Cytoscape to .geojson Objects.
Home-page: https://github.com/Sprum/cytogis
Author: Sprum
Author-email: sprum@hotmail.de
Project-URL: Bug Tracker, https://github.com/Sprum/cytogis/issues
Classifier: Programming Language :: Python :: 3
Classifier: License :: OSI Approved :: MIT License
Classifier: Operating System :: OS Independent
Classifier: Topic :: Scientific/Engineering :: GIS
Requires-Python: >=3.11
License-File: LICENSE
Requires-Dist: pandas >=2.1.4
